jupyterlab_launcher_sections_extension/__init__.py
jupyterlab_launcher_sections_extension/_version.py
jupyterlab_launcher_sections_extension/config.py
jupyterlab_launcher_sections_extension/routes.py
jupyterlab_launcher_sections_extension/labextension/package.json
jupyterlab_launcher_sections_extension/labextension/static/728.e0f1d9b818fda2053cee.js
jupyterlab_launcher_sections_extension/labextension/static/859.078bd3d01687b4508080.js
jupyterlab_launcher_sections_extension/labextension/static/remoteEntry.1769ddc5df2ecd7c3b42.js
jupyterlab_launcher_sections_extension/labextension/static/style.js
jupyterlab_launcher_sections_extension/labextension/static/third-party-licenses.json
jupyterlab_launcher_sections_extension/schema/config.schema.json
jupyterlab_launcher_sections_extension/tests/__init__.py
jupyterlab_launcher_sections_extension/tests/test_routes.py
jupyterlab_launcher_sections_extension-1.0.3.data/data/etc/jupyter/jupyter_server_config.d/jupyterlab_launcher_sections_extension.json
jupyterlab_launcher_sections_extension-1.0.3.data/data/share/jupyter/labextensions/jupyterlab_launcher_sections_extension/package.json
jupyterlab_launcher_sections_extension-1.0.3.data/data/share/jupyter/labextensions/jupyterlab_launcher_sections_extension/static/728.e0f1d9b818fda2053cee.js
jupyterlab_launcher_sections_extension-1.0.3.data/data/share/jupyter/labextensions/jupyterlab_launcher_sections_extension/static/859.078bd3d01687b4508080.js
jupyterlab_launcher_sections_extension-1.0.3.data/data/share/jupyter/labextensions/jupyterlab_launcher_sections_extension/static/remoteEntry.1769ddc5df2ecd7c3b42.js
jupyterlab_launcher_sections_extension-1.0.3.data/data/share/jupyter/labextensions/jupyterlab_launcher_sections_extension/static/style.js
jupyterlab_launcher_sections_extension-1.0.3.data/data/share/jupyter/labextensions/jupyterlab_launcher_sections_extension/static/third-party-licenses.json
jupyterlab_launcher_sections_extension-1.0.3.dist-info/METADATA
jupyterlab_launcher_sections_extension-1.0.3.dist-info/WHEEL
jupyterlab_launcher_sections_extension-1.0.3.dist-info/licenses/LICENSE
jupyterlab_launcher_sections_extension-1.0.3.dist-info/RECORD
