Metadata-Version: 2.4
Name: jupyterlab_launcher_sections_extension
Version: 1.0.3
Summary: Jupyterlab extension to allow setting section-specific icons for the launcher
Project-URL: Homepage, https://github.com/stellarshenson/jupyterlab_launcher_sections_extension
Project-URL: Bug Tracker, https://github.com/stellarshenson/jupyterlab_launcher_sections_extension/issues
Project-URL: Repository, https://github.com/stellarshenson/jupyterlab_launcher_sections_extension.git
Author-email: Stellars Henson <konrad.jelen@gmail.com>
License: BSD 3-Clause License
License-File: LICENSE
Keywords: jupyter,jupyterlab,jupyterlab-extension
Classifier: Framework :: Jupyter
Classifier: Framework :: Jupyter :: JupyterLab
Classifier: Framework :: Jupyter :: JupyterLab :: 4
Classifier: Framework :: Jupyter :: JupyterLab :: Extensions
Classifier: Framework :: Jupyter :: JupyterLab :: Extensions :: Prebuilt
Classifier: License :: OSI Approved :: BSD License
Classifier: Programming Language :: Python
Classifier: Programming Language :: Python :: 3
Classifier: Programming Language :: Python :: 3.10
Classifier: Programming Language :: Python :: 3.11
Classifier: Programming Language :: Python :: 3.12
Classifier: Programming Language :: Python :: 3.13
Classifier: Programming Language :: Python :: 3.14
Requires-Python: >=3.10
Requires-Dist: jsonschema>=4.0
Requires-Dist: jupyter-server<3,>=2.4.0
Requires-Dist: pyyaml>=6.0
Provides-Extra: dev
Provides-Extra: test
Requires-Dist: coverage; extra == 'test'
Requires-Dist: pytest; extra == 'test'
Requires-Dist: pytest-asyncio; extra == 'test'
Requires-Dist: pytest-cov; extra == 'test'
Requires-Dist: pytest-jupyter[server]>=0.6.0; extra == 'test'
